bcj/_bcj.cpython-311-darwin.so
bcj/__init__.py
bcj/_bcjfilter.py
bcj/py.typed
pybcj-1.0.3.dist-info/RECORD
pybcj-1.0.3.dist-info/LICENSE
pybcj-1.0.3.dist-info/WHEEL
pybcj-1.0.3.dist-info/top_level.txt
pybcj-1.0.3.dist-info/METADATA
