Metadata-Version: 2.1
Name: pybcj
Version: 1.0.3
Summary: bcj filter library
Author-email: Hiroshi Miura <miurahr@linux.com>
License: LGPL-2.1-or-later
Project-URL: Source, https://codeberg.org/miurahr/pybcj
Keywords: lzma,bcj
Classifier: Development Status :: 5 - Production/Stable
Classifier: License :: OSI Approved :: GNU Lesser General Public License v2 or later (LGPLv2+)
Classifier: Operating System :: MacOS :: MacOS X
Classifier: Operating System :: Microsoft :: Windows
Classifier: Operating System :: POSIX
Classifier: Operating System :: POSIX :: Linux
Classifier: Programming Language :: Python
Classifier: Programming Language :: Python :: 3
Classifier: Programming Language :: Python :: 3.9
Classifier: Programming Language :: Python :: 3.10
Classifier: Programming Language :: Python :: 3.11
Classifier: Programming Language :: Python :: 3.12
Classifier: Programming Language :: Python :: 3.13
Classifier: Programming Language :: Python :: 3 :: Only
Classifier: Programming Language :: Python :: Implementation :: CPython
Classifier: Programming Language :: Python :: Implementation :: PyPy
Classifier: Topic :: Software Development :: Libraries :: Python Modules
Requires-Python: >=3.9
License-File: LICENSE
Provides-Extra: test
Requires-Dist: pytest>=6.0; extra == "test"
Requires-Dist: pytest-cov; extra == "test"
Requires-Dist: hypothesis; extra == "test"
Requires-Dist: coverage[toml]>=5.2; extra == "test"
Provides-Extra: check
Requires-Dist: mypy>=1.10.0; extra == "check"
Requires-Dist: check-manifest; extra == "check"
Requires-Dist: flake8<5; extra == "check"
Requires-Dist: flake8-black; extra == "check"
Requires-Dist: flake8-colors; extra == "check"
Requires-Dist: flake8-isort; extra == "check"
Requires-Dist: flake8-pyi; extra == "check"
Requires-Dist: flake8-typing-imports; extra == "check"
Requires-Dist: readme-renderer; extra == "check"
Requires-Dist: pygments; extra == "check"
